biz/dfch/ste100parser/__init__.py
biz/dfch/ste100parser/__main__.py
biz/dfch/ste100parser/char.py
biz/dfch/ste100parser/grammar.py
biz/dfch/ste100parser/parser.py
biz/dfch/ste100parser/token.py
biz/dfch/ste100parser/grammar/__init__.py
biz/dfch/ste100parser/grammar/container.lark
biz/dfch/ste100parser/grammar/default.lark
biz/dfch/ste100parser/grammar/fp.lark
biz/dfch/ste100parser/grammar/grammar_type.py
biz/dfch/ste100parser/grammar/integer.lark
biz/dfch/ste100parser/grammar/number.lark
biz/dfch/ste100parser/grammar/word.lark
biz/dfch/ste100parser/serializer/__init__.py
biz/dfch/ste100parser/serializer/container_serializer.py
biz/dfch/ste100parser/transformer/__init__.py
biz/dfch/ste100parser/transformer/container_transformer.py
biz/dfch/ste100parser/transformer/container_transformer_rules.py
biz/dfch/ste100parser/transformer/text_transformer.py
biz/dfch/ste100parser/transformer/text_transformer_rules.py
biz/dfch/ste100parser/transformer/token_converter.py
biz/dfch/ste100parser/transformer/transformer_base.py
biz/dfch/ste100parser/transformer/tree_rewriter.py
biz_dfch_ste100parser-0.1.6.dist-info/licenses/LICENSE
biz_dfch_ste100parser-0.1.6.dist-info/METADATA
biz_dfch_ste100parser-0.1.6.dist-info/WHEEL
biz_dfch_ste100parser-0.1.6.dist-info/entry_points.txt
biz_dfch_ste100parser-0.1.6.dist-info/top_level.txt
biz_dfch_ste100parser-0.1.6.dist-info/RECORD
