Metadata-Version: 2.4
Name: biz-dfch-ste100parser
Version: 0.1.6
Summary: An ASD-STE100 (Simplified Technical English) parser.
Author: Ronald Rink
Maintainer: d-fens GmbH
License-Expression: AGPL-3.0-or-later
Project-URL: Homepage, https://github.com/dfensgmbh/biz.dfch.AsdSte100Parser.git
Project-URL: Issues, https://github.com/dfensgmbh/biz.dfch.AsdSte100Parser/issues
Keywords: ASD-STE100,STE100,STE100 Issue 9,Simplified Technical English,simplified-technical-english,cnl,controlled language,controlled natural language,technical writing,technical-writing,NLP,lark,parser,text processing
Classifier: Development Status :: 4 - Beta
Classifier: Intended Audience :: Science/Research
Classifier: Intended Audience :: Developers
Classifier: Intended Audience :: Information Technology
Classifier: Natural Language :: English
Classifier: Topic :: Text Processing :: Linguistic
Classifier: Topic :: Text Processing :: Markup
Classifier: Topic :: Text Processing :: Markup :: Markdown
Classifier: Topic :: Software Development :: Libraries :: Python Modules
Classifier: Programming Language :: Python
Classifier: Programming Language :: Python :: 3
Classifier: Programming Language :: Python :: 3.11
Classifier: Programming Language :: Python :: 3.12
Classifier: Programming Language :: Python :: 3.13
Requires-Python: >=3.11
License-File: LICENSE
Requires-Dist: lark==1.3.1
Provides-Extra: dev
Requires-Dist: build; extra == "dev"
Dynamic: license-file
